domainfinderbyrohit/__init__.py
domainfinderbyrohit/demo.py
domainfinderbyrohit/trial.py
domainfinderbyrohit/dnsdumpster/API_example.py
domainfinderbyrohit/dnsdumpster/DNSDumpsterAPI.py
domainfinderbyrohit/dnsdumpster/__init__.py
domainfinderbyrohit/dnsdumpster/test_api.py
domainfinderbyrohit-0.0.1.dist-info/LICENSE
domainfinderbyrohit-0.0.1.dist-info/METADATA
domainfinderbyrohit-0.0.1.dist-info/WHEEL
domainfinderbyrohit-0.0.1.dist-info/top_level.txt
domainfinderbyrohit-0.0.1.dist-info/RECORD
